ertis_auth_cli-0.1.0.data/scripts/cli
ertis_auth_cli-0.1.0.data/scripts/ertis_auth_cli
src/__init__.py
ertis_auth_cli-0.1.0.dist-info/LICENSE
ertis_auth_cli-0.1.0.dist-info/METADATA
ertis_auth_cli-0.1.0.dist-info/WHEEL
ertis_auth_cli-0.1.0.dist-info/top_level.txt
ertis_auth_cli-0.1.0.dist-info/RECORD
