Metadata-Version: 2.1
Name: ertis-auth-cli
Version: 0.1.0
Summary: Ertis Auth initializer CLI
Home-page: https://github.com/ismetacar/ertis_auth_cli
Author: ismetacar
Author-email: dismetacar@gmail.com
License: UNKNOWN
Platform: UNKNOWN
Classifier: Programming Language :: Python :: 3
Classifier: License :: OSI Approved :: MIT License
Classifier: Operating System :: OS Independent
